fourmica_sdk/__init__.py
fourmica_sdk/bls_utils.py
fourmica_sdk/client.py
fourmica_sdk/config.py
fourmica_sdk/contract.py
fourmica_sdk/errors.py
fourmica_sdk/guarantee.py
fourmica_sdk/models.py
fourmica_sdk/rpc.py
fourmica_sdk/signing.py
fourmica_sdk/utils.py
fourmica_sdk/x402.py
fourmica_sdk/abi/core4mica.json
fourmica_sdk/abi/erc20.json
sdk_4mica-0.4.3.dist-info/licenses/LICENSE
sdk_4mica-0.4.3.dist-info/METADATA
sdk_4mica-0.4.3.dist-info/WHEEL
sdk_4mica-0.4.3.dist-info/top_level.txt
sdk_4mica-0.4.3.dist-info/RECORD
