Metadata-Version: 2.4
Name: sdk-4mica
Version: 0.4.3
Summary: Python SDK for interacting with the 4Mica payment network.
Author-email: 4Mica Network <mairon.mahzoun@3milabs.tech>
Project-URL: homepage, https://4mica.xyz
Project-URL: repository, https://github.com/4mica-Network/4mica-core
Project-URL: documentation, https://docs.4mica.xyz
Requires-Python: >=3.9
License-File: LICENSE
Requires-Dist: web3>=7.14.0
Requires-Dist: httpx>=0.27.0
Requires-Dist: eth-abi>=5.2.0
Requires-Dist: eth-utils>=5.3.1
Requires-Dist: pydantic>=2.7.0
Requires-Dist: typing-extensions>=4.9.0
Requires-Dist: websockets>=15.0
Provides-Extra: bls
Requires-Dist: py-ecc>=6.0.0; extra == "bls"
Provides-Extra: dev
Requires-Dist: pytest>=9.0.1; extra == "dev"
Requires-Dist: pytest-asyncio>=1.3.0; extra == "dev"
Dynamic: license-file
